{
  "title" : "Das Team",
  "description" : "Wir sind zwei aus Wissenschaft und Forschung stammende Softwaretechnologen,</br>die mit ihrer Erfahrung den Wissenstransfer in die Industrie unterstützen möchten.",
  "members" : [
    {
      "name" : "Karsten Wendt",
      "description" : "Gesellschafter</br>Lösungsdesign",
      "avatar" : "karsten.jpg",
      "social" : {
        "link": { "url": "https://tu-dresden.de/ing/informatik/smt/st", "type": "fa" },
        "xing": { "url": "https://www.xing.com/profile/Karsten_Wendt12/cv", "type": "fab" }
      }
    },
    {
      "name" : "Peter Heisig",
      "description" : "Gesellschafter</br>Implementierung",
      "avatar" : "peter.jpg",
      "social" : {
        "link" : { "url": "https://pehei.de", "type": "fa" },
        "xing": { "url": "https://www.xing.com/profile/Peter_Heisig4/cv", "type": "fab" }
      }
    }
  ]
}
